xontrib/onepath.py
xontrib_onepath-0.4.0.dist-info/LICENSE
xontrib_onepath-0.4.0.dist-info/METADATA
xontrib_onepath-0.4.0.dist-info/WHEEL
xontrib_onepath-0.4.0.dist-info/top_level.txt
xontrib_onepath-0.4.0.dist-info/RECORD
