Metadata-Version: 2.1
Name: xontrib-onepath
Version: 0.4.0
Summary: Associate files with app or alias and run it without preceding commands in xonsh shell.
Home-page: https://github.com/anki-code/xontrib-onepath
Author: anki
Author-email: author@example.com
License: BSD
Project-URL: Documentation, https://github.com/anki-code/xontrib-onepath/blob/master/README.md
Project-URL: Code, https://github.com/anki-code/xontrib-onepath
Project-URL: Issue tracker, https://github.com/anki-code/xontrib-onepath/issues
Platform: any
Classifier: Environment :: Console
Classifier: Intended Audience :: End Users/Desktop
Classifier: Operating System :: OS Independent
Classifier: Programming Language :: Python
Classifier: Programming Language :: Unix Shell
Classifier: Topic :: System :: Shells
Classifier: Topic :: System :: System Shells
Classifier: Topic :: Terminals
Classifier: Topic :: System :: Networking
Classifier: License :: OSI Approved :: BSD License
Requires-Python: >=3.6
License-File: LICENSE
Requires-Dist: python-magic
